ellma/__init__.py
ellma/cli/__init__.py
ellma/cli/main.py
ellma/commands/__init__.py
ellma/commands/audio.py
ellma/commands/base.py
ellma/commands/files/__init__.py
ellma/commands/files/base_operations.py
ellma/commands/files/file_ops.py
ellma/commands/files/read_write.py
ellma/commands/files/search_ops.py
ellma/commands/files.py
ellma/commands/introspection.py
ellma/commands/system/commands/__init__.py
ellma/commands/system/commands/cleanup.py
ellma/commands/system/commands/config.py
ellma/commands/system/commands/health.py
ellma/commands/system/commands/ports.py
ellma/commands/system/commands/processes.py
ellma/commands/system/commands/scan.py
ellma/commands/system/commands/services.py
ellma/commands/system/core/__init__.py
ellma/commands/system/models/__init__.py
ellma/commands/system/utils/__init__.py
ellma/commands/system.py
ellma/commands/web.py
ellma/constants.py
ellma/core/__init__.py
ellma/core/agent.py
ellma/core/decorators.py
ellma/core/error_logger.py
ellma/core/evolution/__init__.py
ellma/core/evolution/config.py
ellma/core/evolution/crossover.py
ellma/core/evolution/engine.py
ellma/core/evolution/exceptions.py
ellma/core/evolution/fitness.py
ellma/core/evolution/mutation.py
ellma/core/evolution/population.py
ellma/core/evolution/selection.py
ellma/core/evolution/utils.py
ellma/core/evolution.py
ellma/core/modular.py
ellma/core/module_generator.py
ellma/core/security.py
ellma/core/shell.py
ellma/generators/__init__.py
ellma/generators/bash.py
ellma/generators/docker.py
ellma/generators/groovy.py
ellma/generators/python.py
ellma/modules/__init__.py
ellma/modules/generated_utils.py
ellma/modules/loader.py
ellma/modules/registry.py
ellma/modules/stt.py
ellma/modules/tts.py
ellma/secure_executor.py
ellma/secure_shell.py
ellma/security/__init__.py
ellma/security/__main__.py
ellma/security/cli.py
ellma/security/core.py
ellma/security/validation.py
ellma/security/validations.py
ellma/utils/__init__.py
ellma/utils/config.py
ellma/utils/error_logger.py
ellma-0.1.20.dist-info/LICENSE
ellma-0.1.20.dist-info/METADATA
ellma-0.1.20.dist-info/WHEEL
ellma-0.1.20.dist-info/RECORD
