Metadata-Version: 2.3
Name: ellma
Version: 0.1.20
Summary: Evolutionary Local LLM Agent - Self-improving AI assistant
License: Apache-2.0
Author: Tom Sapletta
Author-email: info@softreck.dev
Maintainer: WRONAI Team
Maintainer-email: contact@wronai.dev
Requires-Python: >=3.10,<3.14
Classifier: License :: OSI Approved :: Apache Software License
Classifier: Programming Language :: Python :: 3
Classifier: Programming Language :: Python :: 3.10
Classifier: Programming Language :: Python :: 3.11
Classifier: Programming Language :: Python :: 3.12
Classifier: Programming Language :: Python :: 3.13
Provides-Extra: audio
Provides-Extra: dev
Requires-Dist: PyAudio (>=0.2.13) ; extra == "audio"
Requires-Dist: SpeechRecognition (>=3.10.0) ; extra == "audio"
Requires-Dist: bandit (>=1.7.0) ; extra == "dev"
Requires-Dist: black (>=23.0.0) ; extra == "dev"
Requires-Dist: codecov (>=2.1.0) ; extra == "dev"
Requires-Dist: coverage[toml] (>=7.0.0) ; extra == "dev"
Requires-Dist: flake8 (>=6.0.0) ; extra == "dev"
Requires-Dist: flake8-bugbear (>=23.0.0) ; extra == "dev"
Requires-Dist: flake8-docstrings (>=1.7.0) ; extra == "dev"
Requires-Dist: flake8-import-order (>=0.18.2) ; extra == "dev"
Requires-Dist: invoke (>=2.0.0) ; extra == "dev"
Requires-Dist: isort (>=5.12.0) ; extra == "dev"
Requires-Dist: mypy (>=1.0.0) ; extra == "dev"
Requires-Dist: myst-parser (>=2.0.0) ; extra == "dev"
Requires-Dist: pip-tools (>=6.0.0) ; extra == "dev"
Requires-Dist: pre-commit (>=2.20.0) ; extra == "dev"
Requires-Dist: pyaudio (>=0.2.14,<0.3.0)
Requires-Dist: pytest (>=7.0.0) ; extra == "dev"
Requires-Dist: pytest-asyncio (>=0.20.0) ; extra == "dev"
Requires-Dist: pytest-cov (>=4.0.0) ; extra == "dev"
Requires-Dist: pytest-mock (>=3.12.0) ; extra == "dev"
Requires-Dist: safety (>=2.3.0) ; extra == "dev"
Requires-Dist: speechrecognition (>=3.14.3,<4.0.0)
Requires-Dist: sphinx (>=7.0.0) ; extra == "dev"
Requires-Dist: sphinx-autobuild (>=2021.3.14) ; extra == "dev"
Requires-Dist: sphinx-autodoc-typehints (>=1.22.0) ; extra == "dev"
Requires-Dist: sphinx-copybutton (>=0.5.0) ; extra == "dev"
Requires-Dist: sphinx-rtd-theme (>=1.2.0) ; extra == "dev"
Requires-Dist: sphinxcontrib-mermaid (>=0.8.0) ; extra == "dev"
Requires-Dist: tomli (>=2.2.1,<3.0.0)
Requires-Dist: tox (>=4.0.0) ; extra == "dev"
Project-URL: Bug Tracker, https://github.com/wronai/ellma/issues
Project-URL: Changelog, https://github.com/wronai/ellma/blob/main/CHANGELOG.md
Project-URL: Documentation, https://wronai.github.io/ellma
Project-URL: Homepage, https://github.com/wronai/ellma
Project-URL: Repository, https://github.com/wronai/ellma.git
Project-URL: Source, https://github.com/wronai/ellma
